dcs/__init__.py
dcs/__main__.py
dcs/cli.py
dcs/streamer.py
docker_context_streamer-0.0.3.dist-info/DESCRIPTION.rst
docker_context_streamer-0.0.3.dist-info/METADATA
docker_context_streamer-0.0.3.dist-info/RECORD
docker_context_streamer-0.0.3.dist-info/WHEEL
docker_context_streamer-0.0.3.dist-info/entry_points.txt
docker_context_streamer-0.0.3.dist-info/metadata.json
docker_context_streamer-0.0.3.dist-info/top_level.txt
